jposit-0.3.3.dist-info/METADATA
jposit-0.3.3.dist-info/WHEEL
jposit/__init__.py
jposit/demo.py
jposit/jposit.cpython-312-x86_64-linux-gnu.so
jposit-0.3.3.dist-info/RECORD
