Metadata-Version: 2.4
Name: jposit
Version: 0.3.3
Classifier: Programming Language :: Python
Classifier: Programming Language :: Rust
Classifier: License :: OSI Approved :: MIT License
Summary: jposit
Home-Page: https://github.com/urbanij/jposit
Author-email: Franceco Urbani <francescourbanidue@gmail.com>
Requires-Python: >=3.8, <3.14
